python_splitter/__init__.py
python_splitter/image_grouping.py
python_splitter/train_test_split.py
python_splitter-0.0.3.dist-info/LICENSE
python_splitter-0.0.3.dist-info/METADATA
python_splitter-0.0.3.dist-info/WHEEL
python_splitter-0.0.3.dist-info/top_level.txt
python_splitter-0.0.3.dist-info/RECORD
