Metadata-Version: 2.1
Name: python-splitter
Version: 0.0.3
Summary: A package  that Splits Class_Folders to Train, Test, Val folders automatically by shuffling media for machine learning.
Home-page: https://github.com/bharatadk/python_splitter
Author: Bharat Adhikari
Author-email: bharatadk.on@gmail.com
Keywords: folder,splitter
Classifier: Programming Language :: Python :: 3
Classifier: License :: OSI Approved :: MIT License
Classifier: Operating System :: OS Independent
License-File: LICENSE
Requires-Dist: numpy
